{
  "cameraState": {
    "position": [
      146.13616846074123,
      13.450817563338592,
      31.03700653239222
    ],
    "rotation": [
      -0.4089471084491563,
      1.3433310348373486,
      0.3995107288822669,
      "XYZ"
    ],
    "zoom": 7.589554049207456
  },
  "canvasData": [
    {
      "type": "circle",
      "points": [
        {
          "x": 515,
          "y": 327
        },
        {
          "x": 513,
          "y": 279
        },
        {
          "x": 546,
          "y": 365
        }
      ],
      "value": 20.3
    },
    {
      "type": "ruler",
      "points": [
        {
          "x": 532,
          "y": 242
        },
        {
          "x": 633,
          "y": 360
        }
      ],
      "value": 20.5
    },
    {
      "type": "ruler",
      "points": [
        {
          "x": 426,
          "y": 48
        },
        {
          "x": 453,
          "y": 156
        }
      ],
      "value": 14.7
    },
    {
      "type": "brush",
      "points": [
        {
          "x": 530,
          "y": 174
        },
        {
          "x": 530,
          "y": 174
        },
        {
          "x": 531,
          "y": 173
        },
        {
          "x": 533,
          "y": 171
        },
        {
          "x": 539,
          "y": 167
        },
        {
          "x": 548,
          "y": 161
        },
        {
          "x": 556,
          "y": 156
        },
        {
          "x": 562,
          "y": 152
        },
        {
          "x": 566,
          "y": 149
        },
        {
          "x": 567,
          "y": 148
        },
        {
          "x": 568,
          "y": 147
        },
        {
          "x": 568,
          "y": 145
        },
        {
          "x": 568,
          "y": 142
        },
        {
          "x": 567,
          "y": 138
        },
        {
          "x": 566,
          "y": 134
        },
        {
          "x": 563,
          "y": 129
        },
        {
          "x": 559,
          "y": 125
        },
        {
          "x": 555,
          "y": 121
        },
        {
          "x": 551,
          "y": 118
        },
        {
          "x": 548,
          "y": 116
        },
        {
          "x": 545,
          "y": 115
        },
        {
          "x": 543,
          "y": 114
        },
        {
          "x": 541,
          "y": 114
        },
        {
          "x": 539,
          "y": 114
        },
        {
          "x": 537,
          "y": 114
        },
        {
          "x": 537,
          "y": 114
        },
        {
          "x": 537,
          "y": 115
        },
        {
          "x": 538,
          "y": 115
        },
        {
          "x": 541,
          "y": 115
        },
        {
          "x": 545,
          "y": 115
        },
        {
          "x": 548,
          "y": 115
        },
        {
          "x": 551,
          "y": 115
        },
        {
          "x": 552,
          "y": 115
        },
        {
          "x": 553,
          "y": 115
        },
        {
          "x": 554,
          "y": 115
        },
        {
          "x": 554,
          "y": 116
        },
        {
          "x": 553,
          "y": 116
        },
        {
          "x": 553,
          "y": 116
        },
        {
          "x": 553,
          "y": 117
        },
        {
          "x": 553,
          "y": 117
        },
        {
          "x": 553,
          "y": 117
        },
        {
          "x": 553,
          "y": 118
        },
        {
          "x": 555,
          "y": 119
        },
        {
          "x": 558,
          "y": 120
        },
        {
          "x": 562,
          "y": 121
        },
        {
          "x": 567,
          "y": 122
        },
        {
          "x": 571,
          "y": 122
        },
        {
          "x": 575,
          "y": 123
        },
        {
          "x": 579,
          "y": 123
        },
        {
          "x": 583,
          "y": 124
        },
        {
          "x": 586,
          "y": 125
        },
        {
          "x": 588,
          "y": 126
        },
        {
          "x": 588,
          "y": 127
        },
        {
          "x": 589,
          "y": 129
        },
        {
          "x": 589,
          "y": 131
        },
        {
          "x": 589,
          "y": 134
        },
        {
          "x": 589,
          "y": 136
        },
        {
          "x": 589,
          "y": 139
        },
        {
          "x": 592,
          "y": 141
        },
        {
          "x": 597,
          "y": 145
        },
        {
          "x": 602,
          "y": 148
        },
        {
          "x": 606,
          "y": 149
        },
        {
          "x": 608,
          "y": 150
        },
        {
          "x": 610,
          "y": 150
        },
        {
          "x": 610,
          "y": 151
        },
        {
          "x": 610,
          "y": 152
        },
        {
          "x": 609,
          "y": 154
        },
        {
          "x": 608,
          "y": 158
        },
        {
          "x": 607,
          "y": 161
        },
        {
          "x": 606,
          "y": 163
        },
        {
          "x": 606,
          "y": 164
        },
        {
          "x": 606,
          "y": 165
        },
        {
          "x": 607,
          "y": 165
        },
        {
          "x": 609,
          "y": 165
        },
        {
          "x": 610,
          "y": 165
        },
        {
          "x": 611,
          "y": 165
        },
        {
          "x": 611,
          "y": 165
        },
        {
          "x": 611,
          "y": 165
        },
        {
          "x": 611,
          "y": 167
        },
        {
          "x": 611,
          "y": 169
        },
        {
          "x": 610,
          "y": 170
        },
        {
          "x": 610,
          "y": 171
        },
        {
          "x": 610,
          "y": 172
        },
        {
          "x": 610,
          "y": 172
        },
        {
          "x": 612,
          "y": 172
        },
        {
          "x": 615,
          "y": 172
        },
        {
          "x": 617,
          "y": 172
        },
        {
          "x": 618,
          "y": 172
        },
        {
          "x": 618,
          "y": 172
        },
        {
          "x": 619,
          "y": 172
        },
        {
          "x": 619,
          "y": 172
        },
        {
          "x": 619,
          "y": 173
        },
        {
          "x": 621,
          "y": 176
        },
        {
          "x": 624,
          "y": 181
        },
        {
          "x": 630,
          "y": 188
        },
        {
          "x": 635,
          "y": 196
        }
      ],
      "color": "red"
    },
    {
      "type": "brush",
      "points": [
        {
          "x": 705,
          "y": 181
        },
        {
          "x": 705,
          "y": 181
        },
        {
          "x": 703,
          "y": 180
        },
        {
          "x": 699,
          "y": 177
        },
        {
          "x": 696,
          "y": 175
        },
        {
          "x": 692,
          "y": 171
        },
        {
          "x": 689,
          "y": 165
        },
        {
          "x": 686,
          "y": 155
        },
        {
          "x": 685,
          "y": 146
        },
        {
          "x": 684,
          "y": 138
        },
        {
          "x": 684,
          "y": 132
        },
        {
          "x": 684,
          "y": 127
        },
        {
          "x": 687,
          "y": 121
        },
        {
          "x": 695,
          "y": 111
        },
        {
          "x": 705,
          "y": 101
        },
        {
          "x": 710,
          "y": 95
        },
        {
          "x": 715,
          "y": 90
        },
        {
          "x": 722,
          "y": 88
        },
        {
          "x": 734,
          "y": 86
        },
        {
          "x": 747,
          "y": 85
        },
        {
          "x": 759,
          "y": 86
        },
        {
          "x": 767,
          "y": 88
        },
        {
          "x": 771,
          "y": 90
        },
        {
          "x": 774,
          "y": 93
        },
        {
          "x": 778,
          "y": 98
        },
        {
          "x": 784,
          "y": 109
        },
        {
          "x": 794,
          "y": 128
        },
        {
          "x": 803,
          "y": 154
        },
        {
          "x": 809,
          "y": 181
        },
        {
          "x": 811,
          "y": 206
        },
        {
          "x": 812,
          "y": 222
        },
        {
          "x": 811,
          "y": 233
        },
        {
          "x": 809,
          "y": 239
        },
        {
          "x": 804,
          "y": 242
        },
        {
          "x": 796,
          "y": 244
        },
        {
          "x": 784,
          "y": 245
        },
        {
          "x": 771,
          "y": 244
        },
        {
          "x": 758,
          "y": 243
        },
        {
          "x": 746,
          "y": 240
        },
        {
          "x": 734,
          "y": 237
        },
        {
          "x": 720,
          "y": 230
        },
        {
          "x": 705,
          "y": 223
        },
        {
          "x": 689,
          "y": 213
        },
        {
          "x": 675,
          "y": 203
        },
        {
          "x": 667,
          "y": 195
        },
        {
          "x": 662,
          "y": 190
        },
        {
          "x": 660,
          "y": 188
        },
        {
          "x": 660,
          "y": 187
        },
        {
          "x": 660,
          "y": 186
        },
        {
          "x": 661,
          "y": 185
        }
      ],
      "color": "red"
    }
  ]
}